dustapi/__init__.py
dustapi/application.py
dustapi/cli.py
dustapi/helpers.py
dustapi/jwt.py
dustapi/logger.py
dustapi/openapi.py
dustapi/responses.py
dustapi/routing.py
dustapi/sessions.py
dustapi/swagger_ui.py
dustapi/web_sockets.py
dustapi/goha/__init__.py
dustapi/goha/fhe.py
dustapi/goha/sse_engine.py
examples/__init__.py
tests/__init__.py
tests/test_application.py
tests/test_responses.py
tests/test_routing.py
tests/test_websockets.py
dustapi-0.0.7.dist-info/METADATA
dustapi-0.0.7.dist-info/WHEEL
dustapi-0.0.7.dist-info/entry_points.txt
dustapi-0.0.7.dist-info/top_level.txt
dustapi-0.0.7.dist-info/RECORD
