Metadata-Version: 2.1
Name: dustapi
Version: 0.0.7
Summary: Fast light weight web server
Author: Praise G
Requires-Dist: werkzeug
Requires-Dist: jinja2
Requires-Dist: click
Requires-Dist: websockets
Requires-Dist: mkdocs
Requires-Dist: pyjwt
Requires-Dist: typer
Requires-Dist: pydantic
